{
	"classtype": "kTask",
	"internalversion": 17,
	"superclass": "omnistap.kgTAPTask",
	"tvardefs": [

	],
	"cvardefs": [

	],
	"ivardefs": [

	],
	"properties": {
		"collectperformancedata": false,
		"componenticon": 0,
		"componenttype": "kCompStoreHidden",
		"createdate": "2017-10-04 22:17:02",
		"desc": "",
		"editor": "",
		"editordata": "",
		"external": false,
		"issupercomponent": false,
		"moddate": "2017-10-11 22:10:13",
		"showascheckedout": false,
		"userinfo": "",
		"version": ""
	}
}
